pp_cedp/CEDP.py
pp_cedp/Utils.py
pp_cedp/__init__.py
pp_cedp-0.0.5.dist-info/LICENSE
pp_cedp-0.0.5.dist-info/METADATA
pp_cedp-0.0.5.dist-info/WHEEL
pp_cedp-0.0.5.dist-info/top_level.txt
pp_cedp-0.0.5.dist-info/RECORD
