Metadata-Version: 2.1
Name: pp-cedp
Version: 0.0.5
Summary: Privacy-Preserving Continuous Event Data Publishing
Home-page: https://github.com/m4jidRafiei/PP_CEDP
Author: Majid Rafiei
Author-email: majid.rafiei@pads.rwth-aachen.de
License: UNKNOWN
Project-URL: Source, https://github.com/m4jidRafiei/PP_CEDP
Platform: UNKNOWN
Classifier: Programming Language :: Python :: 3
Classifier: License :: OSI Approved :: GNU General Public License v3 (GPLv3)
Classifier: Operating System :: OS Independent
License-File: LICENSE
Requires-Dist: pandas (>=0.24.2)
Requires-Dist: numpy (>=1.18.1)
Requires-Dist: pm4py (>=1.2.10)
